ThePeer/__init__.py
ThePeer/client.py
ThePeer/exceptions.py
ThePeer/schema_conf.py
ThePeer/validators.py
python_thepeer-1.1.0.dist-info/METADATA
python_thepeer-1.1.0.dist-info/WHEEL
python_thepeer-1.1.0.dist-info/top_level.txt
python_thepeer-1.1.0.dist-info/RECORD
